rrpm/__init__.py
rrpm/__main__.py
rrpm/config.py
rrpm/ext/__init__.py
rrpm/ext/loader.py
rrpm/presets/__init__.py
rrpm/presets/base/base.py
rrpm/presets/base/managers.py
rrpm/presets/js.py
rrpm/presets/py.py
rrpm/presets/ts.py
rrpm/rrpm.py
rrpm/utils.py
rrpm-2.0.0.dist-info/entry_points.txt
rrpm-2.0.0.dist-info/LICENSE
rrpm-2.0.0.dist-info/WHEEL
rrpm-2.0.0.dist-info/METADATA
rrpm-2.0.0.dist-info/RECORD
