Metadata-Version: 2.1
Name: rrpm
Version: 2.0.0
Summary: A tool to manage all your projects easily!
Home-page: https://rrpm.vercel.app
License: MIT
Keywords: repository,git,javascript,projects
Author: pybash1
Author-email: pybash@authdeck.xyz
Requires-Python: >=3.7,<4.0
Classifier: Development Status :: 4 - Beta
Classifier: Environment :: Console
Classifier: Intended Audience :: Developers
Classifier: License :: OSI Approved :: MIT License
Classifier: Natural Language :: English
Classifier: Operating System :: OS Independent
Classifier: Programming Language :: Python :: 3
Classifier: Programming Language :: Python :: 3.10
Classifier: Programming Language :: Python :: 3.7
Classifier: Programming Language :: Python :: 3.8
Classifier: Programming Language :: Python :: 3.9
Classifier: Topic :: Software Development :: Version Control
Classifier: Topic :: Software Development :: Version Control :: Git
Classifier: Topic :: Terminals
Classifier: Topic :: Utilities
Requires-Dist: questionary (>=1.10.0,<2.0.0)
Requires-Dist: rich (>=12.4.4,<13.0.0)
Requires-Dist: rrpmpkg (>=1.0.2,<2.0.0)
Requires-Dist: toml (>=0.10.2,<0.11.0)
Requires-Dist: typer (>=0.6.1,<0.7.0)
Project-URL: Bug Tracker, https://github.com/rrpm-org/rrpm/issues
Project-URL: Documentation, https://rrpm.vercel.app
Project-URL: Repository, https://github.com/rrpm-org/rrpm
